[
  {
    "locName": "Montrose Point Bird Sanctuary",
    "howMany": 1,
    "nice_date": "May 31",
    "nice_time": "07:39 PM",
    "checklist": "ebird.org/checklist/S245310637"
  },
  {
    "locName": "Montrose Dunes",
    "howMany": 1,
    "nice_date": "May 31",
    "nice_time": "04:58 PM",
    "checklist": "ebird.org/checklist/S245216208"
  },
  {
    "locName": "Montrose Beach",
    "howMany": 1,
    "nice_date": "May 31",
    "nice_time": "11:43 AM",
    "checklist": "ebird.org/checklist/S245073236"
  },
  {
    "locName": "North Simonds Drive",
    "howMany": 1,
    "nice_date": "May 30",
    "nice_time": "04:32 PM",
    "checklist": "ebird.org/checklist/S244751036"
  },
  {
    "locName": "Montrose Beach",
    "howMany": 3,
    "nice_date": "May 29",
    "nice_time": "03:43 PM",
    "checklist": "ebird.org/checklist/S244321838"
  },
  {
    "locName": "Montrose Beach",
    "howMany": 1,
    "nice_date": "May 26",
    "nice_time": "11:27 PM",
    "checklist": "ebird.org/checklist/S243334834"
  }
]
