[
  {
    "locName": "Montrose Point Bird Sanctuary",
    "howMany": 1,
    "nice_date": "June 4",
    "nice_time": "04:51 PM",
    "checklist": "ebird.org/checklist/S352485822"
  },
  {
    "locName": "Montrose Dunes",
    "howMany": 1,
    "nice_date": "June 4",
    "nice_time": "08:34 AM",
    "checklist": "ebird.org/checklist/S352293328"
  },
  {
    "locName": "Montrose Point",
    "howMany": 1,
    "nice_date": "June 2",
    "nice_time": "05:22 PM",
    "checklist": "ebird.org/checklist/S351606073"
  },
  {
    "locName": "Montrose point bird sanctuary",
    "howMany": 2,
    "nice_date": "May 30",
    "nice_time": "01:37 PM",
    "checklist": "ebird.org/checklist/S349873099"
  },
  {
    "locName": "Montrose Harbor",
    "howMany": 1,
    "nice_date": "May 30",
    "nice_time": "07:46 AM",
    "checklist": "ebird.org/checklist/S349395736"
  },
  {
    "locName": "Montrose Bird Sanctuary",
    "howMany": 1,
    "nice_date": "May 29",
    "nice_time": "05:53 PM",
    "checklist": "ebird.org/checklist/S350578556"
  }
]
